my_package/__init__.py
my_package/extractor.py
my_package/data/BFS.txt
my_package/data/BST.txt
my_package/data/Circular Q.txt
my_package/data/CircularLL.txt
my_package/data/DFS.txt
my_package/data/DoublyLL.txt
my_package/data/Hashing.txt
my_package/data/Heap & Radix.txt
my_package/data/Infix to Postfix.txt
my_package/data/Input_res_Q.txt
my_package/data/LL Operations.txt
my_package/data/Linear Q.txt
my_package/data/Linked List.txt
my_package/data/Output_res_Q.txt
my_package/data/Pol Subtraction.txt
my_package/data/Prefix eval.txt
my_package/data/Priority Queue.txt
my_package/data/Quick & Merge.txt
my_package/data/Selection & Insertion.txt
my_package/data/Stack.txt
my_package/data/Tree Operations.txt
mypackage_assets-0.1.3.dist-info/METADATA
mypackage_assets-0.1.3.dist-info/WHEEL
mypackage_assets-0.1.3.dist-info/top_level.txt
mypackage_assets-0.1.3.dist-info/RECORD
