Metadata-Version: 2.4
Name: mypackage-assets
Version: 0.1.3
Summary: Package that extracts bundled text files
